CHANGES.rst
LICENSE.rst
MANIFEST.in
README.rst
setup.cfg
setup.py
test.rst
src/lineage/__init__.py
src/lineage.controlpanels.egg-info/PKG-INFO
src/lineage.controlpanels.egg-info/SOURCES.txt
src/lineage.controlpanels.egg-info/dependency_links.txt
src/lineage.controlpanels.egg-info/entry_points.txt
src/lineage.controlpanels.egg-info/namespace_packages.txt
src/lineage.controlpanels.egg-info/not-zip-safe
src/lineage.controlpanels.egg-info/requires.txt
src/lineage.controlpanels.egg-info/top_level.txt
src/lineage/controlpanels/__init__.py
src/lineage/controlpanels/actions.py
src/lineage/controlpanels/configure.zcml
src/lineage/controlpanels/interfaces.py
src/lineage/controlpanels/testing.py
src/lineage/controlpanels/profiles/default/actions.xml
src/lineage/controlpanels/profiles/default/browserlayer.xml
src/lineage/controlpanels/profiles/default/controlpanel.xml
src/lineage/controlpanels/profiles/default/metadata.xml
src/lineage/controlpanels/profiles/uninstall/browserlayer.xml
src/lineage/controlpanels/tests/__init__.py
src/lineage/controlpanels/tests/pixel.png
src/lineage/controlpanels/tests/pixelgreen.png
src/lineage/controlpanels/tests/test_controlpanel_browser_site.py
src/lineage/controlpanels/tests/test_robot.py
src/lineage/controlpanels/tests/test_setup.py
src/lineage/controlpanels/tests/robot/test_example.robot