Metadata-Version: 1.1
Name: lineage.controlpanels
Version: 1.0a1
Summary: Plone controlpanels for Lineage sites
Home-page: https://pypi.python.org/pypi/lineage.controlpanels
Author: Johannes Raggam
Author-email: thetetet@gmail.com
License: GPL version 2
Keywords: Python Plone
Platform: UNKNOWN
Classifier: Environment :: Web Environment
Classifier: Framework :: Plone
Classifier: Framework :: Plone :: 5.0
Classifier: Framework :: Plone :: 5.1
Classifier: Programming Language :: Python
Classifier: Programming Language :: Python :: 2.7
Classifier: Operating System :: OS Independent
Classifier: License :: OSI Approved :: GNU General Public License v2 (GPLv2)
